[{"time": 840.3967018127441, "join_order": [9, 2, 5, 1, 19, 11, 8, 10, 18, 4, 3, 15, 17, 0, 12, 6, 7, 13, 16, 14], "costs": 3612134, "fallback": true}, {"time": 1481.7530040740967, "join_order": [9, 5, 16, 2, 1, 19, 3, 15, 11, 18, 8, 17, 0, 12, 6, 7, 13, 10, 4, 14], "costs": 3585858, "fallback": true}, {"time": 2057.393602371216, "join_order": [9, 5, 2, 1, 11, 18, 19, 3, 15, 8, 17, 0, 12, 6, 7, 13, 16, 10, 4, 14], "costs": 3559581, "fallback": true}, {"time": 5505.25, "join_order": [9, 2, 5, 1, 11, 19, 3, 15, 18, 8, 17, 0, 12, 6, 7, 10, 13, 4, 16, 14], "costs": 3539989, "fallback": true}]